README.txt
setup.py
python_wax.egg-info/PKG-INFO
python_wax.egg-info/SOURCES.txt
python_wax.egg-info/dependency_links.txt
python_wax.egg-info/top_level.txt
wax/__init__.py
wax/microjson.py
wax/microjson_test.py
wax/waximpl.py
wax/waximpl_test.py