Metadata-Version: 1.1
Name: python-wax
Version: 0.3
Summary: A hierarchical configuration format and context object for Python
Home-page: http://github.com/phensley/python-wax
Author: Patrick Hensley
Author-email: spaceboy@indirect.com
License: UNKNOWN
Keywords: config,configuration,json,ini
Platform: UNKNOWN
Classifier: Development Status :: 4 - Beta
Classifier: Intended Audience :: Developers
Classifier: License :: OSI Approved :: Apache Software License
Classifier: Programming Language :: Python
Classifier: Programming Language :: Python :: 2.6
Classifier: Programming Language :: Python :: 2.7
Classifier: Topic :: Software Development :: Libraries :: Python Modules
